adzip/__init__.py
adzip/streams.py
adzip/datasets/__init__.py
adzip/datasets/kitti.py
adzip-0.0.1.dist-info/LICENSE
adzip-0.0.1.dist-info/METADATA
adzip-0.0.1.dist-info/WHEEL
adzip-0.0.1.dist-info/top_level.txt
adzip-0.0.1.dist-info/RECORD
