Metadata-Version: 2.1
Name: adzip
Version: 0.0.1
Summary: Holistic data compressor for autonomous driving datasets.
Author-email: Jacob Zhong <cmpute@qq.com>
License: 
Classifier: Development Status :: 2 - Pre-Alpha
Classifier: Intended Audience :: Developers
Classifier: Topic :: System :: Archiving
Classifier: Topic :: System :: Archiving :: Compression
Classifier: License :: OSI Approved :: Apache Software License
Classifier: Programming Language :: Python :: 3
Classifier: Programming Language :: Python :: 3.10
License-File: LICENSE
Requires-Dist: numpy
Requires-Dist: laspy
Requires-Dist: DracoPy
Requires-Dist: pillow
